sqs/__init__.py
sqs/__main__.py
sqs/cnbc/__init__.py
sqs/cnbc/quote_strip.py
sqs/cnbc/stock_quote.py
stock_quote_scraper-0.1.3.dist-info/LICENSE
stock_quote_scraper-0.1.3.dist-info/METADATA
stock_quote_scraper-0.1.3.dist-info/WHEEL
stock_quote_scraper-0.1.3.dist-info/top_level.txt
stock_quote_scraper-0.1.3.dist-info/RECORD
